jquants_derivatives/__init__.py
jquants_derivatives/__main__.py
jquants_derivatives/bsm.py
jquants_derivatives/client.py
jquants_derivatives/database.py
jquants_derivatives/derivatievs.py
jquants_derivatives/models.py
jquants_derivatives-0.3.3.dist-info/METADATA
jquants_derivatives-0.3.3.dist-info/WHEEL
jquants_derivatives-0.3.3.dist-info/RECORD
