Metadata-Version: 2.1
Name: jquants-derivatives
Version: 0.3.3
Summary: J-Quants API Client Derivatives Library
Home-page: https://github.com/drillan/jquants-derivatives
Author: driller
Requires-Python: >=3.10,<4.0
Classifier: Programming Language :: Python :: 3
Classifier: Programming Language :: Python :: 3.10
Classifier: Programming Language :: Python :: 3.11
Requires-Dist: jquants-api-client (>=1.2.0,<2.0.0)
Requires-Dist: plotly (>=5.14.1,<6.0.0)
Requires-Dist: scipy (>=1.11.2,<2.0.0) ; python_version >= "3.10" and python_version < "3.13"
